{
    "show_id": 10687075,
    "show_icon": "http://res03.mengfm.com/deduct_attachment/program/a74/772/071/x4Se0S2tWfvP7peJ.jpg",
    "show_cover": "http://res03.mengfm.com/deduct_attachment/program/a74/772/071/T9ZLg0GnddRk7ww1.jpg",
    "show_times": 0,
    "show_cooper": 0,
    "show_intro": "长得都够不着电话还谈恋爱，现在的小孩子，世风日下哦～",
    "script_id": 231177,
    "user_id": "885928",
    "show_elite": 0,
    "show_self": 0,
    "show_vols": [
        8,
        100,
        46
    ],
    "show_hear": 25,
    "show_listen": 1393,
    "show_comment": 0,
    "show_praise": 0,
    "show_score": 0,
    "show_add_time": 1502176501,
    "show_status": 1,
    "show_script_elite": 0,
    "show_script_essence": 0,
    "show_society_id": 0,
    "show_label": null,
    "show_private": 0,
    "show_mp3": null,
    "show_mp4": null,
    "show_mp4_duration": 0,
    "show_out_listen": 29,
    "show_out_hear": 7,
    "show_best": 0,
    "show_mp4_download": null,
    "project_id": 3324266,
    "channel_id": null,
    "channel_name": null,
    "show_gifts": 0,
    "dialogues": [
        {
            "dialogue_id": 36426566,
            "dialogue_content": "在一个月黑风高的夜晚\n女孩孤零零站在街头",
            "dialogue_delay": 5000,
            "dialogue_image": "http://res03.mengfm.com/deduct_attachment/program/a82/403/292/628f815daf451465.jpg",
            "dialogue_sound": null,
            "dialogue_sound_duration": 0,
            "dialogue_sound_vols": 0,
            "dialogue_bgm": "http://res02.mengfm.com/deduct_attachment/program/a64/404/539/dac18887c6d0dd52.mp3",
            "dialogue_bgm_duration": 267408,
            "dialogue_bgm_vols": 80,
            "dialogue_index": 1,
            "role_id": 0,
            "dialogue_sound_name": null,
            "dialogue_bgm_name": "周玥 - 小幸运 [mqms2].mp3",
            "dialogue_reverb": 0,
            "dialogue_compose": {
                "copyInt": "0",
                "sceneBgUri": "http://res03.meng2u.com/deduct_attachment/program/a72/522/464/f996cb3958b2be34.jpg",
                "sprites": null
            },
            "dialogue_video": null,
            "dialogue_video_duration": 0,
            "dialogue_video_timer": null,
            "phase_bgm": null,
            "phase_bgm_duration": null,
            "phase_sound": null,
            "phase_sound_duration": 5000,
            "role_name": null,
            "phase_video_info": null
        },
        {
            "dialogue_id": 36426567,
            "dialogue_content": "嘟嘟--",
            "dialogue_delay": 0,
            "dialogue_image": "http://res03.mengfm.com/deduct_attachment/program/a82/403/292/ce7924215fff3580.jpg",
            "dialogue_sound": "http://res02.mengfm.com/deduct_attachment/program/sound/15000257435977.mp3",
            "dialogue_sound_duration": 3057,
            "dialogue_sound_vols": 80,
            "dialogue_bgm": null,
            "dialogue_bgm_duration": 0,
            "dialogue_bgm_vols": 0,
            "dialogue_index": 2,
            "role_id": 0,
            "dialogue_sound_name": "电话占线",
            "dialogue_bgm_name": null,
            "dialogue_reverb": 0,
            "dialogue_compose": {
                "copyInt": "0",
                "sceneBgUri": "http://res03.meng2u.com/deduct_attachment/program/a63/959/908/17d0d9cdc9b343e9.jpg",
                "sprites": null
            },
            "dialogue_video": null,
            "dialogue_video_duration": 0,
            "dialogue_video_timer": null,
            "phase_bgm": null,
            "phase_bgm_duration": null,
            "phase_sound": "http://res02.mengfm.com/deduct_attachment/program/sound/15000257435977.mp3",
            "phase_sound_duration": 3057,
            "role_name": null,
            "phase_video_info": null
        },
        {
            "dialogue_id": 36426568,
            "dialogue_content": "歪？别的小朋友都回家了",
            "dialogue_delay": 0,
            "dialogue_image": "http://res03.mengfm.com/deduct_attachment/program/a82/403/292/009ded7a4edba0f6.jpg",
            "dialogue_sound": null,
            "dialogue_sound_duration": 0,
            "dialogue_sound_vols": 0,
            "dialogue_bgm": null,
            "dialogue_bgm_duration": 0,
            "dialogue_bgm_vols": 0,
            "dialogue_index": 3,
            "role_id": 543645,
            "dialogue_sound_name": null,
            "dialogue_bgm_name": null,
            "dialogue_reverb": 0,
            "dialogue_compose": {
                "copyInt": "0",
                "sceneBgUri": "http://res03.meng2u.com/deduct_attachment/program/a72/857/717/b42bdce2db53b41f.jpg",
                "sprites": null
            },
            "dialogue_video": null,
            "dialogue_video_duration": 0,
            "dialogue_video_timer": null,
            "phase_bgm": null,
            "phase_bgm_duration": 0,
            "phase_sound": "http://res02.mengfm.com/deduct_attachment/program/a74/772/071/3ilnsAIBL5kr20DW.mp3",
            "phase_sound_duration": 3553,
            "role_name": "小柠檬",
            "phase_video_info": null
        },
        {
            "dialogue_id": 36426569,
            "dialogue_content": "你怎么还不来接我啊？（可爱俏皮的感觉）",
            "dialogue_delay": 0,
            "dialogue_image": null,
            "dialogue_sound": null,
            "dialogue_sound_duration": 0,
            "dialogue_sound_vols": 0,
            "dialogue_bgm": null,
            "dialogue_bgm_duration": 0,
            "dialogue_bgm_vols": 0,
            "dialogue_index": 4,
            "role_id": 543645,
            "dialogue_sound_name": null,
            "dialogue_bgm_name": null,
            "dialogue_reverb": 0,
            "dialogue_compose": {
                "copyInt": "1",
                "sceneBgUri": "http://res03.meng2u.com/deduct_attachment/program/a72/857/717/b42bdce2db53b41f.jpg",
                "sprites": null
            },
            "dialogue_video": null,
            "dialogue_video_duration": 0,
            "dialogue_video_timer": null,
            "phase_bgm": null,
            "phase_bgm_duration": 0,
            "phase_sound": "http://res02.mengfm.com/deduct_attachment/program/a74/772/071/B7HgclFQQPwssCXj.mp3",
            "phase_sound_duration": 2926,
            "role_name": "小柠檬",
            "phase_video_info": null
        },
        {
            "dialogue_id": 36426570,
            "dialogue_content": "喂喂喂？怎么不说话了？（焦急）\n你是不是自己走丢了呀？",
            "dialogue_delay": 0,
            "dialogue_image": null,
            "dialogue_sound": null,
            "dialogue_sound_duration": 0,
            "dialogue_sound_vols": 0,
            "dialogue_bgm": null,
            "dialogue_bgm_duration": 0,
            "dialogue_bgm_vols": 0,
            "dialogue_index": 5,
            "role_id": 543645,
            "dialogue_sound_name": null,
            "dialogue_bgm_name": null,
            "dialogue_reverb": 0,
            "dialogue_compose": {
                "copyInt": "1",
                "sceneBgUri": "http://res03.meng2u.com/deduct_attachment/program/a72/857/717/b42bdce2db53b41f.jpg",
                "sprites": null
            },
            "dialogue_video": null,
            "dialogue_video_duration": 0,
            "dialogue_video_timer": null,
            "phase_bgm": null,
            "phase_bgm_duration": 0,
            "phase_sound": "http://res02.mengfm.com/deduct_attachment/program/a74/772/071/t3QO1CbHyTMiZ8Px.mp3",
            "phase_sound_duration": 5930,
            "role_name": "小柠檬",
            "phase_video_info": null
        },
        {
            "dialogue_id": 36426571,
            "dialogue_content": "我在。路上堵车了（慌忙的找理由）\n我才没有走丢",
            "dialogue_delay": 0,
            "dialogue_image": "http://res03.mengfm.com/deduct_attachment/program/a82/403/292/79ba463d6ac82e43.jpg",
            "dialogue_sound": null,
            "dialogue_sound_duration": 0,
            "dialogue_sound_vols": 0,
            "dialogue_bgm": null,
            "dialogue_bgm_duration": 0,
            "dialogue_bgm_vols": 0,
            "dialogue_index": 6,
            "role_id": 543646,
            "dialogue_sound_name": null,
            "dialogue_bgm_name": null,
            "dialogue_reverb": 0,
            "dialogue_compose": {
                "copyInt": "0",
                "sceneBgUri": "http://res03.meng2u.com/deduct_attachment/program/a70/983/721/3f9cd8820c17eb85.jpg",
                "sprites": null
            },
            "dialogue_video": null,
            "dialogue_video_duration": 0,
            "dialogue_video_timer": null,
            "phase_bgm": null,
            "phase_bgm_duration": 0,
            "phase_sound": "http://res02.mengfm.com/deduct_attachment/program/a70/320/741/U2MvFqpp0nuLawU9.mp3",
            "phase_sound_duration": 5538,
            "role_name": "大青柚",
            "phase_video_info": null
        },
        {
            "dialogue_id": 36426572,
            "dialogue_content": "只有像你这样活泼的小不点才会走丢呢",
            "dialogue_delay": 0,
            "dialogue_image": null,
            "dialogue_sound": null,
            "dialogue_sound_duration": 0,
            "dialogue_sound_vols": 0,
            "dialogue_bgm": null,
            "dialogue_bgm_duration": 0,
            "dialogue_bgm_vols": 0,
            "dialogue_index": 7,
            "role_id": 543646,
            "dialogue_sound_name": null,
            "dialogue_bgm_name": null,
            "dialogue_reverb": 0,
            "dialogue_compose": {
                "copyInt": "1",
                "sceneBgUri": "http://res03.meng2u.com/deduct_attachment/program/a70/983/721/3f9cd8820c17eb85.jpg",
                "sprites": null
            },
            "dialogue_video": null,
            "dialogue_video_duration": 0,
            "dialogue_video_timer": null,
            "phase_bgm": null,
            "phase_bgm_duration": 0,
            "phase_sound": "http://res02.mengfm.com/deduct_attachment/program/a70/320/741/O5TAiLq99TR3JsfR.mp3",
            "phase_sound_duration": 3579,
            "role_name": "大青柚",
            "phase_video_info": null
        },
        {
            "dialogue_id": 36426573,
            "dialogue_content": "你在哪呢？（平淡无奇）",
            "dialogue_delay": 0,
            "dialogue_image": null,
            "dialogue_sound": null,
            "dialogue_sound_duration": 0,
            "dialogue_sound_vols": 0,
            "dialogue_bgm": null,
            "dialogue_bgm_duration": 0,
            "dialogue_bgm_vols": 0,
            "dialogue_index": 8,
            "role_id": 543646,
            "dialogue_sound_name": null,
            "dialogue_bgm_name": null,
            "dialogue_reverb": 0,
            "dialogue_compose": {
                "copyInt": "1",
                "sceneBgUri": "http://res03.meng2u.com/deduct_attachment/program/a70/983/721/3f9cd8820c17eb85.jpg",
                "sprites": null
            },
            "dialogue_video": null,
            "dialogue_video_duration": 0,
            "dialogue_video_timer": null,
            "phase_bgm": null,
            "phase_bgm_duration": 0,
            "phase_sound": "http://res02.mengfm.com/deduct_attachment/program/a70/320/741/WoPKodzf65Wsu3j3.mp3",
            "phase_sound_duration": 2142,
            "role_name": "大青柚",
            "phase_video_info": null
        },
        {
            "dialogue_id": 36426574,
            "dialogue_content": "嗯..我身上只有一块五了 全都用来打电话了哦\n我够不到电话亭 别的小朋友都有人抱起来了 可是我会踮脚尖喔（读出凄凉孤独的感觉）",
            "dialogue_delay": 0,
            "dialogue_image": "http://res03.mengfm.com/deduct_attachment/program/a82/403/292/ceea316a69cfe6ed.jpg",
            "dialogue_sound": null,
            "dialogue_sound_duration": 0,
            "dialogue_sound_vols": 0,
            "dialogue_bgm": null,
            "dialogue_bgm_duration": 0,
            "dialogue_bgm_vols": 0,
            "dialogue_index": 9,
            "role_id": 543645,
            "dialogue_sound_name": null,
            "dialogue_bgm_name": null,
            "dialogue_reverb": 0,
            "dialogue_compose": {
                "copyInt": "0",
                "sceneBgUri": "http://res03.meng2u.com/deduct_attachment/program/a72/857/717/b42bdce2db53b41f.jpg",
                "sprites": null
            },
            "dialogue_video": null,
            "dialogue_video_duration": 0,
            "dialogue_video_timer": null,
            "phase_bgm": null,
            "phase_bgm_duration": 0,
            "phase_sound": "http://res02.mengfm.com/deduct_attachment/program/a74/772/071/kVTgm9PqD2DLJGOx.mp3",
            "phase_sound_duration": 20167,
            "role_name": "小柠檬",
            "phase_video_info": null
        },
        {
            "dialogue_id": 36426575,
            "dialogue_content": "你在电话亭吗？\n踮着脚..真的好棒哦..（梗塞）",
            "dialogue_delay": 0,
            "dialogue_image": "http://res03.mengfm.com/deduct_attachment/program/a82/403/292/f2de2401f3a55092.jpg",
            "dialogue_sound": null,
            "dialogue_sound_duration": 0,
            "dialogue_sound_vols": 0,
            "dialogue_bgm": null,
            "dialogue_bgm_duration": 0,
            "dialogue_bgm_vols": 0,
            "dialogue_index": 10,
            "role_id": 543646,
            "dialogue_sound_name": null,
            "dialogue_bgm_name": null,
            "dialogue_reverb": 0,
            "dialogue_compose": {
                "copyInt": "0",
                "sceneBgUri": "http://res03.meng2u.com/deduct_attachment/program/a70/983/721/3f9cd8820c17eb85.jpg",
                "sprites": null
            },
            "dialogue_video": null,
            "dialogue_video_duration": 0,
            "dialogue_video_timer": null,
            "phase_bgm": null,
            "phase_bgm_duration": 0,
            "phase_sound": "http://res02.mengfm.com/deduct_attachment/program/a70/320/741/bcjSDCm021xauDgF.mp3",
            "phase_sound_duration": 7367,
            "role_name": "大青柚",
            "phase_video_info": null
        },
        {
            "dialogue_id": 36426576,
            "dialogue_content": "不过要小心 摔倒了我会凶你的",
            "dialogue_delay": 0,
            "dialogue_image": null,
            "dialogue_sound": null,
            "dialogue_sound_duration": 0,
            "dialogue_sound_vols": 0,
            "dialogue_bgm": null,
            "dialogue_bgm_duration": 0,
            "dialogue_bgm_vols": 0,
            "dialogue_index": 11,
            "role_id": 543646,
            "dialogue_sound_name": null,
            "dialogue_bgm_name": null,
            "dialogue_reverb": 0,
            "dialogue_compose": {
                "copyInt": "1",
                "sceneBgUri": "http://res03.meng2u.com/deduct_attachment/program/a70/983/721/3f9cd8820c17eb85.jpg",
                "sprites": null
            },
            "dialogue_video": null,
            "dialogue_video_duration": 0,
            "dialogue_video_timer": null,
            "phase_bgm": null,
            "phase_bgm_duration": 0,
            "phase_sound": "http://res02.mengfm.com/deduct_attachment/program/a70/320/741/sn2mXxLuqbZzgkXV.mp3",
            "phase_sound_duration": 4389,
            "role_name": "大青柚",
            "phase_video_info": null
        },
        {
            "dialogue_id": 36426577,
            "dialogue_content": "乖乖站在原地等我 我过去接你",
            "dialogue_delay": 0,
            "dialogue_image": null,
            "dialogue_sound": null,
            "dialogue_sound_duration": 0,
            "dialogue_sound_vols": 0,
            "dialogue_bgm": null,
            "dialogue_bgm_duration": 0,
            "dialogue_bgm_vols": 0,
            "dialogue_index": 12,
            "role_id": 543646,
            "dialogue_sound_name": null,
            "dialogue_bgm_name": null,
            "dialogue_reverb": 0,
            "dialogue_compose": {
                "copyInt": "1",
                "sceneBgUri": "http://res03.meng2u.com/deduct_attachment/program/a70/983/721/3f9cd8820c17eb85.jpg",
                "sprites": null
            },
            "dialogue_video": null,
            "dialogue_video_duration": 0,
            "dialogue_video_timer": null,
            "phase_bgm": null,
            "phase_bgm_duration": 0,
            "phase_sound": "http://res02.mengfm.com/deduct_attachment/program/a70/320/741/HWBzmR6FxKOIlaML.mp3",
            "phase_sound_duration": 4389,
            "role_name": "大青柚",
            "phase_video_info": null
        },
        {
            "dialogue_id": 36426578,
            "dialogue_content": "我没有钱去买零食啦..可是..我真的..有那么一点点..一点点饿..（无奈 可怜）其实小熊饼干一点都不好吃..",
            "dialogue_delay": 0,
            "dialogue_image": "http://res03.mengfm.com/deduct_attachment/program/a82/403/292/9ed1fbf06aee4064.jpg",
            "dialogue_sound": null,
            "dialogue_sound_duration": 0,
            "dialogue_sound_vols": 0,
            "dialogue_bgm": null,
            "dialogue_bgm_duration": 0,
            "dialogue_bgm_vols": 0,
            "dialogue_index": 13,
            "role_id": 543645,
            "dialogue_sound_name": null,
            "dialogue_bgm_name": null,
            "dialogue_reverb": 0,
            "dialogue_compose": {
                "copyInt": "0",
                "sceneBgUri": "http://res03.meng2u.com/deduct_attachment/program/a72/857/717/b42bdce2db53b41f.jpg",
                "sprites": null
            },
            "dialogue_video": null,
            "dialogue_video_duration": 0,
            "dialogue_video_timer": null,
            "phase_bgm": null,
            "phase_bgm_duration": 0,
            "phase_sound": "http://res02.mengfm.com/deduct_attachment/program/a74/772/071/t53JklUZFb3rjBbJ.mp3",
            "phase_sound_duration": 16666,
            "role_name": "小柠檬",
            "phase_video_info": null
        },
        {
            "dialogue_id": 36426579,
            "dialogue_content": "还有薯片..巧克力棒夹心饼干彩虹糖都不好吃...（心里其实惦记着零食）",
            "dialogue_delay": 0,
            "dialogue_image": null,
            "dialogue_sound": null,
            "dialogue_sound_duration": 0,
            "dialogue_sound_vols": 0,
            "dialogue_bgm": null,
            "dialogue_bgm_duration": 0,
            "dialogue_bgm_vols": 0,
            "dialogue_index": 14,
            "role_id": 543645,
            "dialogue_sound_name": null,
            "dialogue_bgm_name": null,
            "dialogue_reverb": 0,
            "dialogue_compose": {
                "copyInt": "1",
                "sceneBgUri": "http://res03.meng2u.com/deduct_attachment/program/a72/857/717/b42bdce2db53b41f.jpg",
                "sprites": null
            },
            "dialogue_video": null,
            "dialogue_video_duration": 0,
            "dialogue_video_timer": null,
            "phase_bgm": null,
            "phase_bgm_duration": 0,
            "phase_sound": "http://res02.mengfm.com/deduct_attachment/program/a74/772/071/MAPa4g2jt88Sov5U.mp3",
            "phase_sound_duration": 9326,
            "role_name": "小柠檬",
            "phase_video_info": null
        },
        {
            "dialogue_id": 36426580,
            "dialogue_content": "想吃冰激凌吗..（停顿六秒）\n怎么办 我刚刚去冰激凌店 已经卖光了\n我给你买糖葫芦好不好",
            "dialogue_delay": 0,
            "dialogue_image": "http://res03.mengfm.com/deduct_attachment/program/a82/403/292/b94dae8dd5fb8c3e.jpg",
            "dialogue_sound": null,
            "dialogue_sound_duration": 0,
            "dialogue_sound_vols": 0,
            "dialogue_bgm": null,
            "dialogue_bgm_duration": 0,
            "dialogue_bgm_vols": 0,
            "dialogue_index": 15,
            "role_id": 543646,
            "dialogue_sound_name": null,
            "dialogue_bgm_name": null,
            "dialogue_reverb": 0,
            "dialogue_compose": {
                "copyInt": "0",
                "sceneBgUri": "http://res03.meng2u.com/deduct_attachment/program/a70/983/721/3f9cd8820c17eb85.jpg",
                "sprites": null
            },
            "dialogue_video": null,
            "dialogue_video_duration": 0,
            "dialogue_video_timer": null,
            "phase_bgm": null,
            "phase_bgm_duration": 0,
            "phase_sound": "http://res02.mengfm.com/deduct_attachment/program/a70/320/741/Wx04l2wnpflNt8BR.mp3",
            "phase_sound_duration": 15621,
            "role_name": "大青柚",
            "phase_video_info": null
        },
        {
            "dialogue_id": 36426581,
            "dialogue_content": "嗯..喂喂喂..你到哪里了啊",
            "dialogue_delay": 0,
            "dialogue_image": "http://res03.mengfm.com/deduct_attachment/program/a82/403/292/86022a6103d9e2b1.jpg",
            "dialogue_sound": null,
            "dialogue_sound_duration": 0,
            "dialogue_sound_vols": 0,
            "dialogue_bgm": null,
            "dialogue_bgm_duration": 0,
            "dialogue_bgm_vols": 0,
            "dialogue_index": 16,
            "role_id": 543645,
            "dialogue_sound_name": null,
            "dialogue_bgm_name": null,
            "dialogue_reverb": 0,
            "dialogue_compose": {
                "copyInt": "0",
                "sceneBgUri": "http://res03.meng2u.com/deduct_attachment/program/a72/857/717/b42bdce2db53b41f.jpg",
                "sprites": null
            },
            "dialogue_video": null,
            "dialogue_video_duration": 0,
            "dialogue_video_timer": null,
            "phase_bgm": null,
            "phase_bgm_duration": 0,
            "phase_sound": "http://res02.mengfm.com/deduct_attachment/program/a74/772/071/oAQwsQVYGYGzIOPs.mp3",
            "phase_sound_duration": 5825,
            "role_name": "小柠檬",
            "phase_video_info": null
        },
        {
            "dialogue_id": 36426582,
            "dialogue_content": "其实..我今天看见你接别的小朋友回家了哦..（哽咽）",
            "dialogue_delay": 0,
            "dialogue_image": null,
            "dialogue_sound": null,
            "dialogue_sound_duration": 0,
            "dialogue_sound_vols": 0,
            "dialogue_bgm": null,
            "dialogue_bgm_duration": 0,
            "dialogue_bgm_vols": 0,
            "dialogue_index": 17,
            "role_id": 543645,
            "dialogue_sound_name": null,
            "dialogue_bgm_name": null,
            "dialogue_reverb": 0,
            "dialogue_compose": {
                "copyInt": "1",
                "sceneBgUri": "http://res03.meng2u.com/deduct_attachment/program/a72/857/717/b42bdce2db53b41f.jpg",
                "sprites": null
            },
            "dialogue_video": null,
            "dialogue_video_duration": 0,
            "dialogue_video_timer": null,
            "phase_bgm": null,
            "phase_bgm_duration": 0,
            "phase_sound": "http://res02.mengfm.com/deduct_attachment/program/a74/772/071/0CnEfIyA2Gn9RAdW.mp3",
            "phase_sound_duration": 8020,
            "role_name": "小柠檬",
            "phase_video_info": null
        },
        {
            "dialogue_id": 36426583,
            "dialogue_content": "没关系..我可以自己走回去哒..（抽泣）我很厉害哒..",
            "dialogue_delay": 0,
            "dialogue_image": null,
            "dialogue_sound": null,
            "dialogue_sound_duration": 0,
            "dialogue_sound_vols": 0,
            "dialogue_bgm": null,
            "dialogue_bgm_duration": 0,
            "dialogue_bgm_vols": 0,
            "dialogue_index": 18,
            "role_id": 543645,
            "dialogue_sound_name": null,
            "dialogue_bgm_name": null,
            "dialogue_reverb": 0,
            "dialogue_compose": {
                "copyInt": "1",
                "sceneBgUri": "http://res03.meng2u.com/deduct_attachment/program/a72/857/717/b42bdce2db53b41f.jpg",
                "sprites": null
            },
            "dialogue_video": null,
            "dialogue_video_duration": 0,
            "dialogue_video_timer": null,
            "phase_bgm": null,
            "phase_bgm_duration": 0,
            "phase_sound": "http://res02.mengfm.com/deduct_attachment/program/a74/772/071/VZKVofVuNIWuCaGR.mp3",
            "phase_sound_duration": 6609,
            "role_name": "小柠檬",
            "phase_video_info": null
        },
        {
            "dialogue_id": 36426584,
            "dialogue_content": "不是啦..我这里有点吵..（声音越来越低）",
            "dialogue_delay": 0,
            "dialogue_image": "http://res03.mengfm.com/deduct_attachment/program/a82/403/292/5373d18b9275069d.jpg",
            "dialogue_sound": null,
            "dialogue_sound_duration": 0,
            "dialogue_sound_vols": 0,
            "dialogue_bgm": null,
            "dialogue_bgm_duration": 0,
            "dialogue_bgm_vols": 0,
            "dialogue_index": 19,
            "role_id": 543646,
            "dialogue_sound_name": null,
            "dialogue_bgm_name": null,
            "dialogue_reverb": 0,
            "dialogue_compose": {
                "copyInt": "0",
                "sceneBgUri": "http://res03.meng2u.com/deduct_attachment/program/a70/983/721/3f9cd8820c17eb85.jpg",
                "sprites": null
            },
            "dialogue_video": null,
            "dialogue_video_duration": 0,
            "dialogue_video_timer": null,
            "phase_bgm": null,
            "phase_bgm_duration": 0,
            "phase_sound": "http://res02.mengfm.com/deduct_attachment/program/a70/320/741/Pyv9H50qptaKFo5i.mp3",
            "phase_sound_duration": 4885,
            "role_name": "大青柚",
            "phase_video_info": null
        },
        {
            "dialogue_id": 36426585,
            "dialogue_content": "内个..内个.小朋友会炒青菜吗",
            "dialogue_delay": 0,
            "dialogue_image": "http://res03.mengfm.com/deduct_attachment/program/a82/403/292/0d0b168952fcf4b9.jpg",
            "dialogue_sound": null,
            "dialogue_sound_duration": 0,
            "dialogue_sound_vols": 0,
            "dialogue_bgm": null,
            "dialogue_bgm_duration": 0,
            "dialogue_bgm_vols": 0,
            "dialogue_index": 20,
            "role_id": 543645,
            "dialogue_sound_name": null,
            "dialogue_bgm_name": null,
            "dialogue_reverb": 0,
            "dialogue_compose": {
                "copyInt": "0",
                "sceneBgUri": "http://res03.meng2u.com/deduct_attachment/program/a72/857/717/b42bdce2db53b41f.jpg",
                "sprites": null
            },
            "dialogue_video": null,
            "dialogue_video_duration": 0,
            "dialogue_video_timer": null,
            "phase_bgm": null,
            "phase_bgm_duration": 0,
            "phase_sound": "http://res02.mengfm.com/deduct_attachment/program/a74/772/071/ny8qIPEg5DvLqhmr.mp3",
            "phase_sound_duration": 6087,
            "role_name": "小柠檬",
            "phase_video_info": null
        },
        {
            "dialogue_id": 36426586,
            "dialogue_content": "其实..其实刚刚看到有个小朋友手里有两盒冰激凌..\n我问她可不可以卖我一盒..（停顿两秒）\n嗯..买到了..是草莓味的",
            "dialogue_delay": 0,
            "dialogue_image": "http://res03.mengfm.com/deduct_attachment/program/a82/403/292/dd7f05f10f52a5f1.jpg",
            "dialogue_sound": null,
            "dialogue_sound_duration": 0,
            "dialogue_sound_vols": 0,
            "dialogue_bgm": null,
            "dialogue_bgm_duration": 0,
            "dialogue_bgm_vols": 0,
            "dialogue_index": 21,
            "role_id": 543646,
            "dialogue_sound_name": null,
            "dialogue_bgm_name": null,
            "dialogue_reverb": 0,
            "dialogue_compose": {
                "copyInt": "0",
                "sceneBgUri": "http://res03.meng2u.com/deduct_attachment/program/a70/983/721/3f9cd8820c17eb85.jpg",
                "sprites": null
            },
            "dialogue_video": null,
            "dialogue_video_duration": 0,
            "dialogue_video_timer": null,
            "phase_bgm": null,
            "phase_bgm_duration": 0,
            "phase_sound": "http://res02.mengfm.com/deduct_attachment/program/a70/320/741/7pqU5vUR0y3vQhIQ.mp3",
            "phase_sound_duration": 12095,
            "role_name": "大青柚",
            "phase_video_info": null
        },
        {
            "dialogue_id": 36426587,
            "dialogue_content": "我会快点到的..不然冰激凌就化了..",
            "dialogue_delay": 0,
            "dialogue_image": null,
            "dialogue_sound": null,
            "dialogue_sound_duration": 0,
            "dialogue_sound_vols": 0,
            "dialogue_bgm": null,
            "dialogue_bgm_duration": 0,
            "dialogue_bgm_vols": 0,
            "dialogue_index": 22,
            "role_id": 543646,
            "dialogue_sound_name": null,
            "dialogue_bgm_name": null,
            "dialogue_reverb": 0,
            "dialogue_compose": {
                "copyInt": "1",
                "sceneBgUri": "http://res03.meng2u.com/deduct_attachment/program/a70/983/721/3f9cd8820c17eb85.jpg",
                "sprites": null
            },
            "dialogue_video": null,
            "dialogue_video_duration": 0,
            "dialogue_video_timer": null,
            "phase_bgm": null,
            "phase_bgm_duration": 0,
            "phase_sound": "http://res02.mengfm.com/deduct_attachment/program/a70/320/741/0I57E5Goe4pDnuMU.mp3",
            "phase_sound_duration": 4127,
            "role_name": "大青柚",
            "phase_video_info": null
        },
        {
            "dialogue_id": 36426588,
            "dialogue_content": "好..我会在这里等你的..一直等你..\n还有..我很想你.很想很想你..（哽咽）",
            "dialogue_delay": 0,
            "dialogue_image": "http://res03.mengfm.com/deduct_attachment/program/a82/403/292/c5e235733cafecc5.jpg",
            "dialogue_sound": null,
            "dialogue_sound_duration": 0,
            "dialogue_sound_vols": 0,
            "dialogue_bgm": null,
            "dialogue_bgm_duration": 0,
            "dialogue_bgm_vols": 0,
            "dialogue_index": 23,
            "role_id": 543645,
            "dialogue_sound_name": null,
            "dialogue_bgm_name": null,
            "dialogue_reverb": 0,
            "dialogue_compose": {
                "copyInt": "0",
                "sceneBgUri": "http://res03.meng2u.com/deduct_attachment/program/a72/857/717/b42bdce2db53b41f.jpg",
                "sprites": null
            },
            "dialogue_video": null,
            "dialogue_video_duration": 0,
            "dialogue_video_timer": null,
            "phase_bgm": null,
            "phase_bgm_duration": 0,
            "phase_sound": "http://res02.mengfm.com/deduct_attachment/program/a74/772/071/EgZkB4z7q0jPlq6Y.mp3",
            "phase_sound_duration": 12826,
            "role_name": "小柠檬",
            "phase_video_info": null
        },
        {
            "dialogue_id": 36426589,
            "dialogue_content": "也很爱很爱你..我真的会一直等下去..（抽泣）\n不管你会不会来接我..",
            "dialogue_delay": 0,
            "dialogue_image": null,
            "dialogue_sound": null,
            "dialogue_sound_duration": 0,
            "dialogue_sound_vols": 0,
            "dialogue_bgm": null,
            "dialogue_bgm_duration": 0,
            "dialogue_bgm_vols": 0,
            "dialogue_index": 24,
            "role_id": 543645,
            "dialogue_sound_name": null,
            "dialogue_bgm_name": null,
            "dialogue_reverb": 0,
            "dialogue_compose": {
                "copyInt": "1",
                "sceneBgUri": "http://res03.meng2u.com/deduct_attachment/program/a72/857/717/b42bdce2db53b41f.jpg",
                "sprites": null
            },
            "dialogue_video": null,
            "dialogue_video_duration": 0,
            "dialogue_video_timer": null,
            "phase_bgm": null,
            "phase_bgm_duration": 0,
            "phase_sound": "http://res02.mengfm.com/deduct_attachment/program/a74/772/071/EmtDx9po2Sa56OX7.mp3",
            "phase_sound_duration": 10893,
            "role_name": "小柠檬",
            "phase_video_info": null
        },
        {
            "dialogue_id": 36426590,
            "dialogue_content": "不要胡思乱想啦..我只喜欢你一个小不点..\n乖乖等我..不要和陌生人讲话哦",
            "dialogue_delay": 0,
            "dialogue_image": "http://res03.mengfm.com/deduct_attachment/program/a82/403/292/45a6547f8d96e1ac.jpg",
            "dialogue_sound": null,
            "dialogue_sound_duration": 0,
            "dialogue_sound_vols": 0,
            "dialogue_bgm": null,
            "dialogue_bgm_duration": 0,
            "dialogue_bgm_vols": 0,
            "dialogue_index": 25,
            "role_id": 543646,
            "dialogue_sound_name": null,
            "dialogue_bgm_name": null,
            "dialogue_reverb": 0,
            "dialogue_compose": {
                "copyInt": "0",
                "sceneBgUri": "http://res03.meng2u.com/deduct_attachment/program/a70/983/721/3f9cd8820c17eb85.jpg",
                "sprites": null
            },
            "dialogue_video": null,
            "dialogue_video_duration": 0,
            "dialogue_video_timer": null,
            "phase_bgm": null,
            "phase_bgm_duration": 0,
            "phase_sound": "http://res02.mengfm.com/deduct_attachment/program/a70/320/741/0zZjD4db9M8D9MOJ.mp3",
            "phase_sound_duration": 8281,
            "role_name": "大青柚",
            "phase_video_info": null
        },
        {
            "dialogue_id": 36426591,
            "dialogue_content": "你最乖了..",
            "dialogue_delay": 0,
            "dialogue_image": null,
            "dialogue_sound": null,
            "dialogue_sound_duration": 0,
            "dialogue_sound_vols": 0,
            "dialogue_bgm": null,
            "dialogue_bgm_duration": 0,
            "dialogue_bgm_vols": 0,
            "dialogue_index": 26,
            "role_id": 543646,
            "dialogue_sound_name": null,
            "dialogue_bgm_name": null,
            "dialogue_reverb": 0,
            "dialogue_compose": {
                "copyInt": "1",
                "sceneBgUri": "http://res03.meng2u.com/deduct_attachment/program/a70/983/721/3f9cd8820c17eb85.jpg",
                "sprites": null
            },
            "dialogue_video": null,
            "dialogue_video_duration": 0,
            "dialogue_video_timer": null,
            "phase_bgm": null,
            "phase_bgm_duration": 0,
            "phase_sound": "http://res02.mengfm.com/deduct_attachment/program/a70/320/741/eZnsbinnQDtVFWwM.mp3",
            "phase_sound_duration": 1881,
            "role_name": "大青柚",
            "phase_video_info": null
        },
        {
            "dialogue_id": 36426592,
            "dialogue_content": "（低声抽泣）",
            "dialogue_delay": 0,
            "dialogue_image": "http://res03.mengfm.com/deduct_attachment/program/a82/403/292/1ae445b6548807fd.jpg",
            "dialogue_sound": null,
            "dialogue_sound_duration": 0,
            "dialogue_sound_vols": 0,
            "dialogue_bgm": null,
            "dialogue_bgm_duration": 0,
            "dialogue_bgm_vols": 0,
            "dialogue_index": 27,
            "role_id": 543645,
            "dialogue_sound_name": null,
            "dialogue_bgm_name": null,
            "dialogue_reverb": 0,
            "dialogue_compose": {
                "copyInt": "0",
                "sceneBgUri": "http://res03.meng2u.com/deduct_attachment/program/a72/857/717/b42bdce2db53b41f.jpg",
                "sprites": null
            },
            "dialogue_video": null,
            "dialogue_video_duration": 0,
            "dialogue_video_timer": null,
            "phase_bgm": null,
            "phase_bgm_duration": 0,
            "phase_sound": "http://res02.mengfm.com/deduct_attachment/program/a74/772/071/tmmfEp1wOkThPjNJ.mp3",
            "phase_sound_duration": 1985,
            "role_name": "小柠檬",
            "phase_video_info": null
        },
        {
            "dialogue_id": 36426593,
            "dialogue_content": "我怎么听到你哭啊..\n是怕黑吗？站累了？别哭（关切）",
            "dialogue_delay": 0,
            "dialogue_image": "http://res03.mengfm.com/deduct_attachment/program/a82/403/292/74a816eaf527cf4c.jpg",
            "dialogue_sound": null,
            "dialogue_sound_duration": 0,
            "dialogue_sound_vols": 0,
            "dialogue_bgm": null,
            "dialogue_bgm_duration": 0,
            "dialogue_bgm_vols": 0,
            "dialogue_index": 28,
            "role_id": 543646,
            "dialogue_sound_name": null,
            "dialogue_bgm_name": null,
            "dialogue_reverb": 0,
            "dialogue_compose": {
                "copyInt": "0",
                "sceneBgUri": "http://res03.meng2u.com/deduct_attachment/program/a70/983/721/3f9cd8820c17eb85.jpg",
                "sprites": null
            },
            "dialogue_video": null,
            "dialogue_video_duration": 0,
            "dialogue_video_timer": null,
            "phase_bgm": null,
            "phase_bgm_duration": 0,
            "phase_sound": "http://res02.mengfm.com/deduct_attachment/program/a70/320/741/lTtcK1BwHFfoix7x.mp3",
            "phase_sound_duration": 8829,
            "role_name": "大青柚",
            "phase_video_info": null
        },
        {
            "dialogue_id": 36426594,
            "dialogue_content": "我没有哭..我只是..只是有点小感冒..（哽咽）\n你怎么一直喘气啊？",
            "dialogue_delay": 0,
            "dialogue_image": "http://res03.mengfm.com/deduct_attachment/program/a82/403/292/b55f27de64c52a36.jpg",
            "dialogue_sound": null,
            "dialogue_sound_duration": 0,
            "dialogue_sound_vols": 0,
            "dialogue_bgm": null,
            "dialogue_bgm_duration": 0,
            "dialogue_bgm_vols": 0,
            "dialogue_index": 29,
            "role_id": 543645,
            "dialogue_sound_name": null,
            "dialogue_bgm_name": null,
            "dialogue_reverb": 0,
            "dialogue_compose": {
                "copyInt": "0",
                "sceneBgUri": "http://res03.meng2u.com/deduct_attachment/program/a72/857/717/b42bdce2db53b41f.jpg",
                "sprites": null
            },
            "dialogue_video": null,
            "dialogue_video_duration": 0,
            "dialogue_video_timer": null,
            "phase_bgm": null,
            "phase_bgm_duration": 0,
            "phase_sound": "http://res02.mengfm.com/deduct_attachment/program/a74/772/071/w7F6u8kPGh4K73zo.mp3",
            "phase_sound_duration": 10449,
            "role_name": "小柠檬",
            "phase_video_info": null
        },
        {
            "dialogue_id": 36426595,
            "dialogue_content": "我快到了..跑的有点快..所以在喘（呼吸更加急促）",
            "dialogue_delay": 0,
            "dialogue_image": "http://res03.mengfm.com/deduct_attachment/program/a82/403/292/d24288a3e34b23b9.jpg",
            "dialogue_sound": null,
            "dialogue_sound_duration": 0,
            "dialogue_sound_vols": 0,
            "dialogue_bgm": null,
            "dialogue_bgm_duration": 0,
            "dialogue_bgm_vols": 0,
            "dialogue_index": 30,
            "role_id": 543646,
            "dialogue_sound_name": null,
            "dialogue_bgm_name": null,
            "dialogue_reverb": 0,
            "dialogue_compose": {
                "copyInt": "0",
                "sceneBgUri": "http://res03.meng2u.com/deduct_attachment/program/a70/983/721/3f9cd8820c17eb85.jpg",
                "sprites": null
            },
            "dialogue_video": null,
            "dialogue_video_duration": 0,
            "dialogue_video_timer": null,
            "phase_bgm": null,
            "phase_bgm_duration": 0,
            "phase_sound": "http://res02.mengfm.com/deduct_attachment/program/a70/320/741/D4PPP182j1NxxkhF.mp3",
            "phase_sound_duration": 8882,
            "role_name": "大青柚",
            "phase_video_info": null
        },
        {
            "dialogue_id": 36426596,
            "dialogue_content": "哒哒--",
            "dialogue_delay": 0,
            "dialogue_image": "http://res03.mengfm.com/deduct_attachment/program/a82/403/292/8bf60a516cabf6e9.jpg",
            "dialogue_sound": "http://res02.mengfm.com/deduct_attachment/program/sound/15000256931329.mp3",
            "dialogue_sound_duration": 1437,
            "dialogue_sound_vols": 80,
            "dialogue_bgm": null,
            "dialogue_bgm_duration": 0,
            "dialogue_bgm_vols": 0,
            "dialogue_index": 31,
            "role_id": 0,
            "dialogue_sound_name": "跑步声",
            "dialogue_bgm_name": null,
            "dialogue_reverb": 0,
            "dialogue_compose": {
                "copyInt": "0",
                "sceneBgUri": "http://res03.meng2u.com/deduct_attachment/program/a63/959/908/17d0d9cdc9b343e9.jpg",
                "sprites": null
            },
            "dialogue_video": null,
            "dialogue_video_duration": 0,
            "dialogue_video_timer": null,
            "phase_bgm": null,
            "phase_bgm_duration": 0,
            "phase_sound": "http://res02.mengfm.com/deduct_attachment/program/sound/15000256931329.mp3",
            "phase_sound_duration": 1437,
            "role_name": null,
            "phase_video_info": null
        },
        {
            "dialogue_id": 36426597,
            "dialogue_content": "嗯..我已经看见你了..\n那我挂电话了...（若无其事）",
            "dialogue_delay": 0,
            "dialogue_image": "http://res03.mengfm.com/deduct_attachment/program/a82/403/292/b06a73573db21d95.jpg",
            "dialogue_sound": null,
            "dialogue_sound_duration": 0,
            "dialogue_sound_vols": 0,
            "dialogue_bgm": null,
            "dialogue_bgm_duration": 0,
            "dialogue_bgm_vols": 0,
            "dialogue_index": 32,
            "role_id": 543645,
            "dialogue_sound_name": null,
            "dialogue_bgm_name": null,
            "dialogue_reverb": 0,
            "dialogue_compose": {
                "copyInt": "0",
                "sceneBgUri": "http://res03.meng2u.com/deduct_attachment/program/a72/857/717/b42bdce2db53b41f.jpg",
                "sprites": null
            },
            "dialogue_video": null,
            "dialogue_video_duration": 0,
            "dialogue_video_timer": null,
            "phase_bgm": null,
            "phase_bgm_duration": 0,
            "phase_sound": "http://res02.mengfm.com/deduct_attachment/program/a74/772/071/tkcw0wM2Qnzja4bf.mp3",
            "phase_sound_duration": 6269,
            "role_name": "小柠檬",
            "phase_video_info": null
        },
        {
            "dialogue_id": 36426598,
            "dialogue_content": "不用讲再见了..好吧..\n再见..马上就要见了..（读的缓慢些）",
            "dialogue_delay": 0,
            "dialogue_image": null,
            "dialogue_sound": null,
            "dialogue_sound_duration": 0,
            "dialogue_sound_vols": 0,
            "dialogue_bgm": null,
            "dialogue_bgm_duration": 0,
            "dialogue_bgm_vols": 0,
            "dialogue_index": 33,
            "role_id": 543645,
            "dialogue_sound_name": null,
            "dialogue_bgm_name": null,
            "dialogue_reverb": 0,
            "dialogue_compose": {
                "copyInt": "1",
                "sceneBgUri": "http://res03.meng2u.com/deduct_attachment/program/a72/857/717/b42bdce2db53b41f.jpg",
                "sprites": null
            },
            "dialogue_video": null,
            "dialogue_video_duration": 0,
            "dialogue_video_timer": null,
            "phase_bgm": null,
            "phase_bgm_duration": 0,
            "phase_sound": "http://res02.mengfm.com/deduct_attachment/program/a74/772/071/wk4qdUFzV3qNIpWN.mp3",
            "phase_sound_duration": 9848,
            "role_name": "小柠檬",
            "phase_video_info": null
        },
        {
            "dialogue_id": 36426599,
            "dialogue_content": "你再也不是我的盖世英雄。",
            "dialogue_delay": 5000,
            "dialogue_image": "http://res03.mengfm.com/deduct_attachment/program/a82/403/292/3af46bf806cc1c4d.jpg",
            "dialogue_sound": null,
            "dialogue_sound_duration": 0,
            "dialogue_sound_vols": 0,
            "dialogue_bgm": null,
            "dialogue_bgm_duration": 0,
            "dialogue_bgm_vols": 0,
            "dialogue_index": 34,
            "role_id": 0,
            "dialogue_sound_name": null,
            "dialogue_bgm_name": null,
            "dialogue_reverb": 0,
            "dialogue_compose": {
                "copyInt": "0",
                "sceneBgUri": "http://res03.meng2u.com/deduct_attachment/program/a72/522/464/f996cb3958b2be34.jpg",
                "sprites": null
            },
            "dialogue_video": null,
            "dialogue_video_duration": 0,
            "dialogue_video_timer": null,
            "phase_bgm": null,
            "phase_bgm_duration": 0,
            "phase_sound": null,
            "phase_sound_duration": 5000,
            "role_name": null,
            "phase_video_info": null
        }
    ],
    "dialogue_durations": 243878,
    "script_info": {
        "script_id": 231177,
        "script_name": "别的小朋友都回家了",
        "script_icon": "http://res03.mengfm.com/deduct_attachment/program/a62/842/319/2035bad1b46a37fc.jpg",
        "script_cover": "http://res03.mengfm.com/deduct_attachment/program/a62/842/319/2035bad1b46a37fc.jpg",
        "script_dialogue": 34,
        "script_show": 283,
        "script_intro": "歪 你在吗 是我 我有事跟你讲 你先别挂电话啦 听我把话讲完 很短哒 我身上只有一块五啦 都全部用来打电话了 电话亭我够不到 别的小朋友都有人抱起来 不过我会踮脚哦 我今天看见你接别的小朋友回家了哦 没关系 我可以自己回去哒 我很厉害哒 但是我要回自己的家了啦 不去你那里了哦 我",
        "user_id": "3354857",
        "script_elite": 0,
        "script_comment": 2,
        "script_praise": 9,
        "script_add_time": 1502103961,
        "script_edit_time": 1501995194,
        "script_reason": null,
        "script_status": 1,
        "script_edit_status": 0,
        "script_source": 3,
        "script_essence": 0,
        "script_label": [
            "经典",
            "催泪",
            "感人"
        ],
        "script_diffi": 1,
        "script_role_num": 2,
        "script_series_id": 0,
        "script_society_id": 0,
        "script_idea_id": 0,
        "script_idea_recom": 0,
        "script_tort": 0,
        "script_from": "android",
        "script_video": 0,
        "script_pay_gold": 0,
        "script_cate_info": [
            {
                "column_id": 116,
                "column_name": "现代",
                "column_icon": "14458302594809.png",
                "column_parent": "类型",
                "column_index": 1,
                "column_top": 0,
                "column_add_time": 1434684020,
                "column_status": 1,
                "column_user_select": 1,
                "column_order": 8
            }
        ],
        "script_style_info": [
            {
                "column_id": 118,
                "column_name": "泪目",
                "column_icon": "14455954749788.jpg",
                "column_parent": "风格",
                "column_index": 2,
                "column_top": 0,
                "column_add_time": 1442386820,
                "column_status": 1,
                "column_user_select": 1,
                "column_order": 11
            },
            {
                "column_id": 185,
                "column_name": "温馨日常",
                "column_icon": "1470975506666.jpg",
                "column_parent": "风格",
                "column_index": 2,
                "column_top": 0,
                "column_add_time": 1470975506,
                "column_status": 1,
                "column_user_select": 1,
                "column_order": 9
            },
            {
                "column_id": 200,
                "column_name": "励志",
                "column_icon": null,
                "column_parent": "风格",
                "column_index": 2,
                "column_top": 0,
                "column_add_time": 1531983429,
                "column_status": 1,
                "column_user_select": 1,
                "column_order": 8
            }
        ],
        "script_space_info": [
            {
                "column_id": 112,
                "column_name": "中篇",
                "column_icon": "14455953337369.jpg",
                "column_parent": "篇幅",
                "column_index": 3,
                "column_top": 0,
                "column_add_time": 1431938774,
                "column_status": 1,
                "column_user_select": 1,
                "column_order": 0
            }
        ],
        "script_role": [
            {
                "role_id": 543645,
                "role_name": "小柠檬",
                "role_sex": 2,
                "role_intro": "软萌萌的妹子 声音有些难演绎",
                "script_id": 231177,
                "role_icon": "http://res03.mengfm.com/deduct_attachment/program/a63/663/291/6117e0831a9fc149.jpg",
                "role_sound": [
                    "168",
                    "169"
                ]
            },
            {
                "role_id": 543646,
                "role_name": "大青柚",
                "role_sex": 1,
                "role_intro": "霸气大总攻 然而有些花心",
                "script_id": 231177,
                "role_icon": "http://res03.mengfm.com/deduct_attachment/program/a83/584/954/5448b2a9db58bab7.jpg",
                "role_sound": [
                    "164",
                    "167"
                ]
            }
        ],
        "script_author": {
            "user_id": 3354857,
            "script_id": 231177,
            "images": null,
            "content": null,
            "images_url": null
        },
        "user_info": {
            "user_id": "3354857",
            "user_sex": 2,
            "user_name": "苏阿娇.",
            "user_icon": "http://res.mengfm.com/user_icon/a93/744/481/Ja5RC9eOmjJ16wrZ.jpg",
            "user_sign": "剧渣勿喷",
            "user_level": 15,
            "user_sound": "少女 妖姬 ",
            "user_score": 1173,
            "user_member": 0,
            "user_year_member": null,
            "user_member_status": 0,
            "vin": {
                "vin_group": false,
                "vin_group_type": null,
                "vin_group_id": null
            },
            "level_rank": "新晋新秀",
            "level_honor": [
                "http://res.mengfm.com/deduct_attachment/level_icon/2.png"
            ],
            "items": null
        },
        "roles": [
            {
                "role_id": 543645,
                "user_id": "885928",
                "cooper_lead": 1,
                "user_sex": 2,
                "user_name": "小拇指",
                "user_icon": "http://res.mengfm.com/user_icon/a93/064/907/0CZo2aTeqZQJffvJ.jpg",
                "user_level": 35,
                "user_sound": null,
                "user_score": 6445,
                "user_member": 0,
                "user_year_member": null,
                "user_member_status": 0,
                "vin": {
                    "vin_group": false,
                    "vin_group_type": null,
                    "vin_group_id": null
                },
                "level_rank": "资深新秀",
                "level_honor": [
                    "http://res.mengfm.com/deduct_attachment/level_icon/2.png",
                    "http://res.mengfm.com/deduct_attachment/level_icon/2.png",
                    "http://res.mengfm.com/deduct_attachment/level_icon/2.png"
                ],
                "items": null,
                "role_name": "小柠檬"
            },
            {
                "role_id": 543646,
                "user_id": "446114",
                "cooper_lead": 0,
                "user_sex": 1,
                "user_name": "曾经的一楠",
                "user_icon": "http://res.mengfm.com/user_icon/a119/120/945/fnlzCwzv2dEOyRm1.jpg",
                "user_level": 38,
                "user_sound": "小受 青年 ",
                "user_score": 7545,
                "user_member": 0,
                "user_year_member": null,
                "user_member_status": 0,
                "vin": {
                    "vin_group": false,
                    "vin_group_type": null,
                    "vin_group_id": null
                },
                "level_rank": "资深新秀",
                "level_honor": [
                    "http://res.mengfm.com/deduct_attachment/level_icon/2.png",
                    "http://res.mengfm.com/deduct_attachment/level_icon/2.png",
                    "http://res.mengfm.com/deduct_attachment/level_icon/2.png"
                ],
                "items": null,
                "role_name": "大青柚"
            }
        ]
    },
    "show_role": [
        {
            "role_id": 543645,
            "user_id": "885928",
            "cooper_lead": 1,
            "user_sex": 2,
            "user_name": "小拇指",
            "user_icon": "http://res.mengfm.com/user_icon/a93/064/907/0CZo2aTeqZQJffvJ.jpg",
            "user_level": 35,
            "user_sound": null,
            "user_score": 6445,
            "user_member": 0,
            "user_year_member": null,
            "user_member_status": 0,
            "vin": {
                "vin_group": false,
                "vin_group_type": null,
                "vin_group_id": null
            },
            "level_rank": "资深新秀",
            "level_honor": [
                "http://res.mengfm.com/deduct_attachment/level_icon/2.png",
                "http://res.mengfm.com/deduct_attachment/level_icon/2.png",
                "http://res.mengfm.com/deduct_attachment/level_icon/2.png"
            ],
            "items": null,
            "role_name": "小柠檬"
        },
        {
            "role_id": 543646,
            "user_id": "446114",
            "cooper_lead": 0,
            "user_sex": 1,
            "user_name": "曾经的一楠",
            "user_icon": "http://res.mengfm.com/user_icon/a119/120/945/fnlzCwzv2dEOyRm1.jpg",
            "user_level": 38,
            "user_sound": "小受 青年 ",
            "user_score": 7545,
            "user_member": 0,
            "user_year_member": null,
            "user_member_status": 0,
            "vin": {
                "vin_group": false,
                "vin_group_type": null,
                "vin_group_id": null
            },
            "level_rank": "资深新秀",
            "level_honor": [
                "http://res.mengfm.com/deduct_attachment/level_icon/2.png",
                "http://res.mengfm.com/deduct_attachment/level_icon/2.png",
                "http://res.mengfm.com/deduct_attachment/level_icon/2.png"
            ],
            "items": null,
            "role_name": "大青柚"
        }
    ],
    "user_info": {
        "user_sex": 2,
        "user_id": "885928",
        "user_name": "小拇指",
        "user_icon": "http://res.mengfm.com/user_icon/a93/064/907/0CZo2aTeqZQJffvJ.jpg",
        "user_level": 35,
        "level": {
            "level_id": 35,
            "level_rank": "资深新秀",
            "level_honor": [
                "http://res.mengfm.com/deduct_attachment/level_icon/2.png",
                "http://res.mengfm.com/deduct_attachment/level_icon/2.png",
                "http://res.mengfm.com/deduct_attachment/level_icon/2.png"
            ],
            "level_score": 6120,
            "level_show": 0
        },
        "fans": null
    },
    "record_score": 1900,
    "items": null,
    "is_collect": 0,
    "user_praise": 0,
    "user_show_count": 0,
    "user_script_count": 0,
    "gift_enable": true,
    "series_info": null,
    "forward_users": {
        "list": null,
        "total": 0
    },
    "is_show_video": 1
}